gitizi/__init__.py
gitizi/cli.py
gitizi/exceptions.py
gitizi/util.py
gitizi/ai/__init__.py
gitizi/ai/context/__init__.py
gitizi/ai/context/squash.py
gitizi-0.2.7.dist-info/LICENSE
gitizi-0.2.7.dist-info/METADATA
gitizi-0.2.7.dist-info/WHEEL
gitizi-0.2.7.dist-info/entry_points.txt
gitizi-0.2.7.dist-info/top_level.txt
gitizi-0.2.7.dist-info/RECORD
