Metadata-Version: 2.1
Name: gitizi
Version: 0.2.7
Summary: Easy and useful git commands
Author-email: Radoslaw Gryta <radek.gryta@gmail.com>
Project-URL: Homepage, https://github.com/rgryta/gitizi
Project-URL: Bug Tracker, https://github.com/rgryta/gitizi/issues
Classifier: Programming Language :: Python :: 3
Classifier: License :: OSI Approved :: MIT License
Classifier: Operating System :: OS Independent
Requires-Python: >=3.11
License-File: LICENSE
Requires-Dist: click
Requires-Dist: g4f
Requires-Dist: GitPython
Provides-Extra: dev
Requires-Dist: staging ; extra == 'dev'
Requires-Dist: black ; extra == 'dev'
Requires-Dist: isort ; extra == 'dev'
Requires-Dist: noprint ; extra == 'dev'
Requires-Dist: pylint ; extra == 'dev'
Requires-Dist: bump-my-version ; extra == 'dev'
Requires-Dist: mock ; extra == 'dev'
Requires-Dist: pytest ; extra == 'dev'
Requires-Dist: pytest-sugar ; extra == 'dev'
Requires-Dist: pytest-xdist ; extra == 'dev'
Requires-Dist: pytest-asyncio ; extra == 'dev'
Requires-Dist: pytest-timeout ; extra == 'dev'
Requires-Dist: coverage[toml] ; extra == 'dev'
